{"url":"https:\/\/alliance-group.bitrix24.ru\/rest\/1\/0gqh0szrbpm7e49t\/crm.deal.add.json","info":{"url":"https:\/\/alliance-group.bitrix24.ru\/rest\/1\/0gqh0szrbpm7e49t\/crm.deal.add.json","content_type":"application\/json; charset=utf-8","http_code":200,"header_size":1030,"request_size":212,"filetime":-1,"ssl_verify_result":0,"redirect_count":0,"total_time":0.808406,"namelookup_time":0.000951,"connect_time":0.011555,"pretransfer_time":0.048385,"size_upload":233,"size_download":288,"speed_download":356,"speed_upload":288,"download_content_length":-1,"upload_content_length":233,"starttransfer_time":0.048769,"redirect_time":0,"redirect_url":"","primary_ip":"178.132.201.51","certinfo":[],"primary_port":443,"local_ip":"31.31.196.39","local_port":35582,"http_version":3,"protocol":2,"ssl_verifyresult":0,"scheme":"HTTPS","appconnect_time_us":46843,"connect_time_us":11555,"namelookup_time_us":951,"pretransfer_time_us":48385,"redirect_time_us":0,"starttransfer_time_us":48769,"total_time_us":808406},"params":{"method":"crm.deal.add","params":{"FIELDS":{"CATEGORY_ID":0,"SOURCE_ID":"WEB","TITLE":"\u0417\u0430\u044f\u0432\u043a\u0430 \u0441 \u0441\u0430\u0439\u0442\u0430 dom-club.com +7 (991) 711-96-64 [19.03.2025 16:04]","CONTACT_ID":52}}},"result":{"result":140,"time":{"start":1742389466.286393,"finish":1742389466.981925,"duration":0.6955320835113525,"processing":0.6617519855499268,"date_start":"2025-03-19T16:04:26+03:00","date_finish":"2025-03-19T16:04:26+03:00","operating_reset_at":1742390066,"operating":0.6617200374603271}}}