{"url":"https:\/\/alliance-group.bitrix24.ru\/rest\/1\/0gqh0szrbpm7e49t\/crm.deal.add.json","info":{"url":"https:\/\/alliance-group.bitrix24.ru\/rest\/1\/0gqh0szrbpm7e49t\/crm.deal.add.json","content_type":"application\/json; charset=utf-8","http_code":200,"header_size":1034,"request_size":212,"filetime":-1,"ssl_verify_result":0,"redirect_count":0,"total_time":1.058637,"namelookup_time":0.000846,"connect_time":0.003813,"pretransfer_time":0.0204,"size_upload":234,"size_download":285,"speed_download":269,"speed_upload":221,"download_content_length":-1,"upload_content_length":234,"starttransfer_time":0.020918,"redirect_time":0,"redirect_url":"","primary_ip":"46.235.53.67","certinfo":[],"primary_port":443,"local_ip":"31.31.196.39","local_port":46318,"http_version":3,"protocol":2,"ssl_verifyresult":0,"scheme":"HTTPS","appconnect_time_us":19589,"connect_time_us":3813,"namelookup_time_us":846,"pretransfer_time_us":20400,"redirect_time_us":0,"starttransfer_time_us":20918,"total_time_us":1058637},"params":{"method":"crm.deal.add","params":{"FIELDS":{"CATEGORY_ID":0,"SOURCE_ID":"WEB","TITLE":"\u0417\u0430\u044f\u0432\u043a\u0430 \u0441 \u0441\u0430\u0439\u0442\u0430 dom-club.com +7 (916) 102-46-81 [24.03.2025 11:20]","CONTACT_ID":278}}},"result":{"result":332,"time":{"start":1742804416.224447,"finish":1742804417.210973,"duration":0.9865260124206543,"processing":0.9455230236053467,"date_start":"2025-03-24T11:20:16+03:00","date_finish":"2025-03-24T11:20:17+03:00","operating_reset_at":1742805016,"operating":0.9454951286315918}}}